README.md
lektor_git_repos.py
setup.cfg
setup.py
lektor_git_repos.egg-info/PKG-INFO
lektor_git_repos.egg-info/SOURCES.txt
lektor_git_repos.egg-info/dependency_links.txt
lektor_git_repos.egg-info/entry_points.txt
lektor_git_repos.egg-info/requires.txt
lektor_git_repos.egg-info/top_level.txt