Metadata-Version: 1.0
Name: lektor-git-repos
Version: 0.1.1
Summary: Fetches your Git repos for display in Lektor templates
Home-page: https://git.com/marksteve/lektor-git-repos
Author: Mark Steve Samson
Author-email: hello@marksteve.com
License: MIT
Platform: UNKNOWN
